rscope/README.md
rscope/__init__.py
rscope/__main__.py
rscope/brax.py
rscope/config.py
rscope/event_handler.py
rscope/event_handler_test.py
rscope/image_processing.py
rscope/image_processing_test.py
rscope/main.py
rscope/main_test.py
rscope/model_loader.py
rscope/rollout.py
rscope/rollout_test.py
rscope/rscope_utils.py
rscope/ssh_utils.py
rscope/ssh_utils_test.py
rscope/state.py
rscope/test_utils.py
rscope/viewer_utils.py
rscope-0.0.8.dist-info/METADATA
rscope-0.0.8.dist-info/WHEEL
rscope-0.0.8.dist-info/licenses/LICENSE
rscope-0.0.8.dist-info/RECORD
